cin_validator/__init__.py
cin_validator/__main__.py
cin_validator/cin_validator.py
cin_validator/england_holidates.py
cin_validator/ingress.py
cin_validator/rule_engine/__api.py
cin_validator/rule_engine/__context.py
cin_validator/rule_engine/__init__.py
cin_validator/rule_engine/__registry.py
cin_validator/rules/__init__.py
cin_validator/rules/cin2022_23/__init__.py
cin_validator/rules/cin2022_23/rule_100.py
cin_validator/rules/cin2022_23/rule_1103.py
cin_validator/rules/cin2022_23/rule_1104.py
cin_validator/rules/cin2022_23/rule_1105.py
cin_validator/rules/cin2022_23/rule_1510.py
cin_validator/rules/cin2022_23/rule_1520.py
cin_validator/rules/cin2022_23/rule_1530.py
cin_validator/rules/cin2022_23/rule_1540.py
cin_validator/rules/cin2022_23/rule_1550.py
cin_validator/rules/cin2022_23/rule_1560Q.py
cin_validator/rules/cin2022_23/rule_2883.py
cin_validator/rules/cin2022_23/rule_2884.py
cin_validator/rules/cin2022_23/rule_2885.py
cin_validator/rules/cin2022_23/rule_2886Q.py
cin_validator/rules/cin2022_23/rule_2887Q.py
cin_validator/rules/cin2022_23/rule_2888Q.py
cin_validator/rules/cin2022_23/rule_2889.py
cin_validator/rules/cin2022_23/rule_2990.py
cin_validator/rules/cin2022_23/rule_2991Q.py
cin_validator/rules/cin2022_23/rule_4000.py
cin_validator/rules/cin2022_23/rule_4001.py
cin_validator/rules/cin2022_23/rule_4003.py
cin_validator/rules/cin2022_23/rule_4004.py
cin_validator/rules/cin2022_23/rule_4008.py
cin_validator/rules/cin2022_23/rule_4009Q.py
cin_validator/rules/cin2022_23/rule_4010.py
cin_validator/rules/cin2022_23/rule_4011.py
cin_validator/rules/cin2022_23/rule_4012Q.py
cin_validator/rules/cin2022_23/rule_4013.py
cin_validator/rules/cin2022_23/rule_4014.py
cin_validator/rules/cin2022_23/rule_4015.py
cin_validator/rules/cin2022_23/rule_4016.py
cin_validator/rules/cin2022_23/rule_4017.py
cin_validator/rules/cin2022_23/rule_4180.py
cin_validator/rules/cin2022_23/rule_4220.py
cin_validator/rules/cin2022_23/rule_8500.py
csc_validator_be_cin-0.1.7.dist-info/METADATA
csc_validator_be_cin-0.1.7.dist-info/WHEEL
csc_validator_be_cin-0.1.7.dist-info/RECORD
