Metadata-Version: 2.1
Name: csc-validator-be-cin
Version: 0.1.7
Summary: Shared module for validating CIN census data using DfE rules.
Home-page: https://github.com/data-to-insight/csc-validator-be-cin
License: MIT
Author: Tambe Tabitha
Author-email: tambe.tabitha@socialfinance.org.uk
Requires-Python: >=3.9,<4.0
Classifier: License :: OSI Approved :: MIT License
Classifier: Programming Language :: Python :: 3
Classifier: Programming Language :: Python :: 3.9
Classifier: Programming Language :: Python :: 3.10
Classifier: Programming Language :: Python :: 3.11
Classifier: Programming Language :: Python :: 3.12
Classifier: Programming Language :: Python :: 3.13
Requires-Dist: click-log (>=0.4.0,<0.5.0)
Requires-Dist: govuk-bank-holidays (>=0.13,<0.14)
Requires-Dist: pandas (>=1.4.2,<2.0.0)
Requires-Dist: prpc-python (>=0.9.2,<0.10.0)
Requires-Dist: rich (>=13.5.3,<14.0.0)
Requires-Dist: testfixtures (>=7.1.0,<8.0.0)
Project-URL: Repository, https://github.com/data-to-insight/csc-validator-be-cin
